{
    "enabled": true,
    "neededInstalledMods": [],
    "neededUninstalledMods": [],
    "spawns": [
        {
            "id": "rockruff-1",
            "pokemon": "rockruff",
            "presets": [
                "natural"
            ],
            "type": "pokemon",
            "context": "grounded",
            "bucket": "uncommon",
            "level": "8-25",
            "weight": 6.2,
            "condition": {
                "minSkyLight": 8,
                "maxSkyLight": 15,
                "biomes": [
                    "#cobblemon:is_mountain"
                ]
            }
        },
        {
            "id": "rockruff-2",
            "pokemon": "rockruff wolf_form=dusk",
            "presets": [
                "natural"
            ],
            "type": "pokemon",
            "context": "grounded",
            "bucket": "uncommon",
            "level": "8-25",
            "weight": 0.413,
            "condition": {
                "minSkyLight": 8,
                "maxSkyLight": 15,
                "biomes": [
                    "#cobblemon:is_mountain"
                ]
            }
        }
    ]
}
