{"format_version":"1.12.0","minecraft:geometry":[{"description":{"identifier":"geometry.unknown","texture_width":256,"texture_height":256,"visible_bounds_width":6,"visible_bounds_height":4.5,"visible_bounds_offset":[0,1.75,0]},"bones":[{"name":"altaria","pivot":[0,0,0]},{"name":"body","parent":"altaria","pivot":[0,15.5,-2],"cubes":[{"origin":[-4.5,8.5,-2],"size":[9,7,10],"uv":[42,81]},{"origin":[2.5,10.5,-0.5],"size":[4,6,6],"uv":[106,60]},{"origin":[-6.5,10.5,-0.5],"size":[4,6,6],"uv":[106,48]},{"origin":[-7.5,4,-2],"size":[15,7,11],"uv":[0,67]}]},{"name":"torso","parent":"body","pivot":[0,15.5,-2],"cubes":[{"origin":[-4,10.5,-6],"size":[8,5,4],"uv":[18,85]},{"origin":[-4.5,7,-9.5],"size":[9,9,4],"uv":[0,54]},{"origin":[-6.5,5.5,-6.5],"size":[13,8,6],"uv":[80,82]},{"origin":[1.5,13.5,-6.5],"size":[4,4,6],"uv":[32,116]},{"origin":[-5.5,13.5,-6.5],"size":[4,4,6],"uv":[108,26]}]},{"name":"neck","parent":"torso","pivot":[0,15.5,-6],"cubes":[{"origin":[-2,15.5,-8],"size":[4,8,4],"uv":[118,36]}]},{"name":"head","parent":"neck","pivot":[0,23,-6],"cubes":[{"origin":[-3.5,23,-10],"size":[7,6,7],"uv":[36,0]},{"origin":[3,23.5,-10.5],"size":[1,2,2],"uv":[64,9]},{"origin":[-4,23.5,-10.5],"size":[1,2,2],"uv":[26,63]}]},{"name":"right_eye","parent":"head","pivot":[-7,9,-3],"cubes":[{"origin":[-2.5,25,-10.01],"size":[1,2,0],"uv":[40,4]}]},{"name":"left_eye","parent":"head","pivot":[7,9,-3],"cubes":[{"origin":[1.5,25,-10.01],"size":[1,2,0],"uv":[0,39]}]},{"name":"right_eye_closed","parent":"head","pivot":[-7,9,-3],"cubes":[{"origin":[-2.5,25,-9.92],"size":[1,2,0],"uv":[0,2]}]},{"name":"left_eye_closed","parent":"head","pivot":[7,9,-3],"cubes":[{"origin":[1.5,25,-9.92],"size":[1,2,0],"uv":[0,0]}]},{"name":"beak","parent":"head","pivot":[0,7,-3],"cubes":[{"origin":[-2,23,-12],"size":[4,2,2],"uv":[0,9]}]},{"name":"jaw","parent":"beak","pivot":[0,23,-10],"cubes":[{"origin":[-2,23,-12],"size":[4,0,2],"uv":[0,39]}]},{"name":"feather_right","parent":"head","pivot":[0,29,-6.75],"rotation":[0,0,-5],"cubes":[{"origin":[-1,29,-6.5],"size":[1,1,0],"uv":[2,13]},{"origin":[-1.5,30,-6.5],"size":[2,6,0],"uv":[4,85]}]},{"name":"feather_right_bend","parent":"feather_right","pivot":[-0.5,36,-6.5],"cubes":[{"origin":[-1.5,36,-6.5],"size":[2,6,0],"uv":[0,85]}]},{"name":"feather_right_end","parent":"feather_right_bend","pivot":[-0.5,42,-6.5],"cubes":[{"origin":[-1.5,42,-6.5],"size":[2,4,0],"uv":[22,54]}]},{"name":"feather_right_tip","parent":"feather_right_end","pivot":[-0.5,46,-6.5],"cubes":[{"origin":[-1.5,46,-6.5],"size":[2,2,0],"uv":[30,63]},{"origin":[-1,48,-6.5],"size":[1,2,0],"uv":[0,9]}]},{"name":"feather_left","parent":"head","pivot":[0,29,-6.75],"rotation":[0,0,5],"cubes":[{"origin":[0,29,-6.5],"size":[1,1,0],"uv":[0,13]},{"origin":[-0.5,30,-6.5],"size":[2,6,0],"uv":[82,81]}]},{"name":"feather_left_bend","parent":"feather_left","pivot":[0.5,36,-6.5],"cubes":[{"origin":[-0.5,36,-6.5],"size":[2,6,0],"uv":[0,67]}]},{"name":"feather_left_end","parent":"feather_left_bend","pivot":[0.5,42,-6.5],"cubes":[{"origin":[-0.5,42,-6.5],"size":[2,4,0],"uv":[0,54]}]},{"name":"feather_left_tip","parent":"feather_left_end","pivot":[0.5,46,-6.5],"cubes":[{"origin":[-0.5,46,-6.5],"size":[2,2,0],"uv":[10,39]},{"origin":[0,48,-6.5],"size":[1,2,0],"uv":[0,4]}]},{"name":"right_arm","parent":"torso","pivot":[-6.5,11.5,-1.5],"cubes":[{"origin":[-9.5,6.5,-6.5],"size":[4,10,10],"inflate":0.01,"uv":[70,96]},{"origin":[-20.5,5,-8.5],"size":[11,13,14],"uv":[36,40]},{"origin":[-9.5,5.5,-1.5],"size":[0,12,7],"pivot":[-9.5,12.25,-1.5],"rotation":[0,12.5,0],"uv":[104,7]},{"origin":[-9.5,5.5,-8.5],"size":[0,12,7],"pivot":[-9.5,12.25,-1.5],"rotation":[0,-12.5,0],"uv":[46,103]},{"origin":[-20.5,18,-8.5],"size":[9,0,14],"pivot":[-20.5,18,-1.5],"rotation":[0,0,-15],"uv":[76,0]},{"origin":[-20.5,5,-8.5],"size":[9,0,14],"pivot":[-20.5,5,-1.5],"rotation":[0,0,15],"uv":[74,68]},{"origin":[-20.5,5,-8.5],"size":[9,13,0],"pivot":[-20.5,11.5,-8.5],"rotation":[0,15,0],"uv":[118,13]},{"origin":[-20.5,5,5.5],"size":[9,13,0],"pivot":[-20.5,11.5,5.5],"rotation":[0,-15,0],"uv":[78,116]}]},{"name":"right_elbow","parent":"right_arm","pivot":[-20.5,11.5,-1.5],"cubes":[{"origin":[-31.5,5,-8.5],"size":[11,13,14],"uv":[36,13]},{"origin":[-31.5,5.5,-1.5],"size":[0,12,7],"pivot":[-31.5,12.25,-1.5],"rotation":[0,-12.5,0],"uv":[98,101]},{"origin":[-31.5,5.5,-8.5],"size":[0,12,7],"pivot":[-31.5,12.25,-1.5],"rotation":[0,12.5,0],"uv":[98,89]},{"origin":[-29.5,18,-8.5],"size":[9,0,14],"pivot":[-20.5,18,-1.5],"rotation":[0,0,15],"uv":[74,54]},{"origin":[-29.5,5,-8.5],"size":[9,0,14],"pivot":[-20.5,5,-1.5],"rotation":[0,0,-15],"uv":[72,14]},{"origin":[-29.5,5,-8.5],"size":[9,13,0],"pivot":[-20.5,11.5,-8.5],"rotation":[0,-15,0],"uv":[60,116]},{"origin":[-29.5,5,5.5],"size":[9,13,0],"pivot":[-20.5,11.5,5.5],"rotation":[0,15,0],"uv":[14,115]},{"origin":[-35.5,6.5,-6.5],"size":[4,10,10],"uv":[18,95]}]},{"name":"left_arm","parent":"torso","pivot":[6.5,11.5,-1.5],"cubes":[{"origin":[5.5,6.5,-6.5],"size":[4,10,10],"inflate":0.01,"uv":[90,28]},{"origin":[9.5,5,-8.5],"size":[11,13,14],"uv":[0,27]},{"origin":[9.5,5.5,-1.5],"size":[0,12,7],"pivot":[9.5,12.25,-1.5],"rotation":[0,-12.5,0],"uv":[0,98]},{"origin":[9.5,5.5,-8.5],"size":[0,12,7],"pivot":[9.5,12.25,-1.5],"rotation":[0,12.5,0],"uv":[46,91]},{"origin":[11.5,18,-8.5],"size":[9,0,14],"pivot":[20.5,18,-1.5],"rotation":[0,0,15],"uv":[56,67]},{"origin":[11.5,5,-8.5],"size":[9,0,14],"pivot":[20.5,5,-1.5],"rotation":[0,0,-15],"uv":[38,67]},{"origin":[11.5,5,-8.5],"size":[9,13,0],"pivot":[20.5,11.5,-8.5],"rotation":[0,-15,0],"uv":[112,109]},{"origin":[11.5,5,5.5],"size":[9,13,0],"pivot":[20.5,11.5,5.5],"rotation":[0,15,0],"uv":[112,96]}]},{"name":"left_elbow","parent":"left_arm","pivot":[20.5,11.5,-1.5],"cubes":[{"origin":[20.5,5,-8.5],"size":[11,13,14],"uv":[0,0]},{"origin":[31.5,5.5,-1.5],"size":[0,12,7],"pivot":[31.5,12.25,-1.5],"rotation":[0,12.5,0],"uv":[72,7]},{"origin":[31.5,5.5,-8.5],"size":[0,12,7],"pivot":[31.5,12.25,-1.5],"rotation":[0,-12.5,0],"uv":[0,20]},{"origin":[20.5,18,-8.5],"size":[9,0,14],"pivot":[20.5,18,-1.5],"rotation":[0,0,-15],"uv":[58,40]},{"origin":[20.5,5,-8.5],"size":[9,0,14],"pivot":[20.5,5,-1.5],"rotation":[0,0,15],"uv":[58,0]},{"origin":[20.5,5,-8.5],"size":[9,13,0],"pivot":[20.5,11.5,-8.5],"rotation":[0,15,0],"uv":[112,72]},{"origin":[20.5,5,5.5],"size":[9,13,0],"pivot":[20.5,11.5,5.5],"rotation":[0,-15,0],"uv":[108,0]},{"origin":[31.5,6.5,-6.5],"size":[4,10,10],"uv":[0,85]}]},{"name":"right_leg","parent":"body","pivot":[-3,4,-1],"cubes":[{"origin":[-3.5,0,-1.5],"size":[1,4,1],"uv":[48,72]}]},{"name":"right_leg2","parent":"right_leg","pivot":[-4,0,1.5]},{"name":"right_foot","parent":"right_leg2","pivot":[-3,0,-1],"cubes":[{"origin":[-4.5,0.01,-2.5],"size":[3,0,3],"uv":[0,3]},{"origin":[-4,0.01,0.5],"size":[2,0,1],"uv":[4,8]}]},{"name":"right_toes","parent":"right_foot","pivot":[-3,0,-2.5],"cubes":[{"origin":[-4.5,0.01,-3.5],"size":[3,0,1],"uv":[0,7]},{"origin":[-2,0.01,-5],"size":[1,0,2],"inflate":0.01,"uv":[38,2]},{"origin":[-5,0.01,-5],"size":[1,0,2],"inflate":0.01,"uv":[38,0]},{"origin":[-3.5,0.01,-5.5],"size":[1,0,2],"uv":[10,11]}]},{"name":"left_leg","parent":"body","pivot":[3,4,-1],"cubes":[{"origin":[2.5,0,-1.5],"size":[1,4,1],"uv":[3,72]}]},{"name":"left_leg2","parent":"left_leg","pivot":[3,0,-1]},{"name":"left_foot","parent":"left_leg2","pivot":[3,0,-1],"cubes":[{"origin":[1.5,0.01,-2.5],"size":[3,0,3],"uv":[0,0]},{"origin":[2,0.01,0.5],"size":[2,0,1],"uv":[0,8]}]},{"name":"left_toes","parent":"left_foot","pivot":[3,0,-2.5],"cubes":[{"origin":[1.5,0.01,-3.5],"size":[3,0,1],"uv":[0,6]},{"origin":[1,0.01,-5],"size":[1,0,2],"inflate":0.01,"uv":[10,9]},{"origin":[4,0.01,-5],"size":[1,0,2],"inflate":0.01,"uv":[8,9]},{"origin":[2.5,0.01,-5.5],"size":[1,0,2],"uv":[5,6]}]},{"name":"tail","parent":"body","pivot":[0,12,8]},{"name":"tail_right","parent":"tail","pivot":[-1,12,8],"cubes":[{"origin":[-3,12,8],"size":[2,0,9],"inflate":0.02,"uv":[32,67]}]},{"name":"tail_right_bend","parent":"tail_right","pivot":[-2,12,17],"cubes":[{"origin":[-3,12,17],"size":[2,0,9],"inflate":0.02,"uv":[59,0]}]},{"name":"tail_right_end","parent":"tail_right_bend","pivot":[-2,12,26],"cubes":[{"origin":[-3,12,26],"size":[2,0,9],"inflate":0.02,"uv":[55,0]}]},{"name":"tail_left","parent":"tail","pivot":[1,12,8],"cubes":[{"origin":[1,12,8],"size":[2,0,9],"inflate":0.02,"uv":[21,54]}]},{"name":"tail_left_bend","parent":"tail_left","pivot":[2,12,17],"cubes":[{"origin":[1,12,17],"size":[2,0,9],"inflate":0.02,"uv":[17,54]}]},{"name":"tail_left_end","parent":"tail_left_bend","pivot":[2,12,26],"cubes":[{"origin":[1,12,26],"size":[2,0,9],"inflate":0.02,"uv":[0,0]}]},{"name":"tail_mid","parent":"tail","pivot":[0,12,8],"cubes":[{"origin":[-1,12,8],"size":[2,0,6],"inflate":0.01,"uv":[68,81]}]},{"name":"tail_mid_bend","parent":"tail_mid","pivot":[0,12,14],"cubes":[{"origin":[-1,12,14],"size":[2,0,6],"inflate":0.01,"uv":[72,81]}]},{"name":"tail_mid_end","parent":"tail_mid_bend","pivot":[0,12,20],"cubes":[{"origin":[-1,12,20],"size":[2,0,7],"inflate":0.01,"uv":[29,0]}]},{"name":"tail_mid_right","parent":"tail","pivot":[-1.5,12,8],"cubes":[{"origin":[-2.5,12,8],"size":[2,0,6],"uv":[64,81]}]},{"name":"tail_mid_right_bend","parent":"tail_mid_right","pivot":[-1.5,12,14],"cubes":[{"origin":[-2.5,12,14],"size":[2,0,6],"uv":[80,34]}]},{"name":"tail_mid_right_end","parent":"tail_mid_right_bend","pivot":[-1.5,12,20],"cubes":[{"origin":[-2.5,12,20],"size":[2,0,6],"uv":[80,28]}]},{"name":"tail_mid_left","parent":"tail","pivot":[1.5,12,8],"cubes":[{"origin":[0.5,12,8],"size":[2,0,6],"uv":[39,67]}]},{"name":"tail_mid_left_bend","parent":"tail_mid_left","pivot":[1.5,12,14],"cubes":[{"origin":[0.5,12,14],"size":[2,0,6],"uv":[0,67]}]},{"name":"tail_mid_left_end","parent":"tail_mid_left_bend","pivot":[1.5,12,20],"cubes":[{"origin":[0.5,12,20],"size":[2,0,6],"uv":[51,0]}]}]}]}